external_dependency/en_core_web_sm-any-py3-none-any.whl
saged/__init__.py
saged/_assembler.py
saged/_diagnoser.py
saged/_extractor.py
saged/_generator.py
saged/_pipeline.py
saged/_saged_data.py
saged/_scrape.py
saged/_utility.py
sagedbias-0.0.12.dist-info/METADATA
sagedbias-0.0.12.dist-info/WHEEL
sagedbias-0.0.12.dist-info/RECORD
